blockstore/__init__.py
blockstore/urls.py
blockstore/wsgi.py
blockstore/apps/__init__.py
blockstore/apps/api/__init__.py
blockstore/apps/api/apps.py
blockstore/apps/api/data.py
blockstore/apps/api/exceptions.py
blockstore/apps/api/methods.py
blockstore/apps/bundles/__init__.py
blockstore/apps/bundles/admin.py
blockstore/apps/bundles/apps.py
blockstore/apps/bundles/links.py
blockstore/apps/bundles/models.py
blockstore/apps/bundles/storage.py
blockstore/apps/bundles/store.py
blockstore/apps/bundles/management/__init__.py
blockstore/apps/bundles/management/commands/__init__.py
blockstore/apps/bundles/management/commands/createbundle.py
blockstore/apps/bundles/management/commands/createbundleversion.py
blockstore/apps/bundles/management/commands/createcollection.py
blockstore/apps/bundles/migrations/0001_initial.py
blockstore/apps/bundles/migrations/0002_create_drafts.py
blockstore/apps/bundles/migrations/0003_update_character_set.py
blockstore/apps/bundles/migrations/0004_alter_bundle_collection.py
blockstore/apps/bundles/migrations/__init__.py
blockstore/apps/core/__init__.py
blockstore/apps/core/admin.py
blockstore/apps/core/constants.py
blockstore/apps/core/context_processors.py
blockstore/apps/core/models.py
blockstore/apps/core/views.py
blockstore/apps/core/migrations/0001_initial.py
blockstore/apps/core/migrations/0002_auto_20200915_1203.py
blockstore/apps/core/migrations/0003_alter_user_first_name.py
blockstore/apps/core/migrations/__init__.py
blockstore/apps/mysql_unicode/__init__.py
blockstore/apps/mysql_unicode/migrations/0001_initial.py
blockstore/apps/mysql_unicode/migrations/__init__.py
blockstore/apps/rest_api/__init__.py
blockstore/apps/rest_api/constants.py
blockstore/apps/rest_api/permissions.py
blockstore/apps/rest_api/relations.py
blockstore/apps/rest_api/routers.py
blockstore/apps/rest_api/urls.py
blockstore/apps/rest_api/v1/__init__.py
blockstore/apps/rest_api/v1/urls.py
blockstore/apps/rest_api/v1/serializers/__init__.py
openedx_blockstore-1.4.0.dist-info/AUTHORS
openedx_blockstore-1.4.0.dist-info/LICENSE
openedx_blockstore-1.4.0.dist-info/METADATA
openedx_blockstore-1.4.0.dist-info/WHEEL
openedx_blockstore-1.4.0.dist-info/top_level.txt
openedx_blockstore-1.4.0.dist-info/RECORD
