Metadata-Version: 2.1
Name: openedx-blockstore
Version: 1.4.0
Summary: Blockstore is a storage system for learning content in Open edX.
Home-page: https://github.com/openedx/blockstore
License: AGPL 3.0
Keywords: Python edx
Platform: UNKNOWN
Classifier: Development Status :: 3 - Alpha
Classifier: Framework :: Django
Classifier: Framework :: Django :: 3.2
Classifier: Intended Audience :: Developers
Classifier: License :: OSI Approved :: GNU Affero General Public License v3 or later (AGPLv3+)
Classifier: Natural Language :: English
Classifier: Programming Language :: Python :: 3
Classifier: Programming Language :: Python :: 3.8
Requires-Python: >=3.8
Requires-Dist: djangorestframework
Requires-Dist: django
Requires-Dist: edx-auth-backends
Requires-Dist: edx-api-doc-tools
Requires-Dist: drf-nested-routers
Requires-Dist: sqlparse
Requires-Dist: django-filter
Requires-Dist: edx-django-utils
Requires-Dist: edx-django-release-util
Requires-Dist: mysqlclient
Requires-Dist: attrs
Requires-Dist: django-environ
Requires-Dist: django-waffle
Requires-Dist: pytz
